{
	"records": [
		{
			"select": true,
			"K_B_12": "[0,1)",
			"recid": 0,
			"K_B_00": "2"
		}
	],
	"regulations": {
		"B": [
			"A",
			"B"
		],
		"A": [
			"B"
		]
	},
	"show": {
		"toolbar": true,
		"selectColumn": false,
		"toolbarSave": false,
		"toolbarReload": false,
		"toolbarSearch": false,
		"toolbarColumns": false,
		"toolbarAdd": false,
		"toolbarDelete": false
	},
	"columns": [
		{
			"field": "select",
			"caption": " ",
			"size": "25px",
			"resizable": false,
			"editable": {
				"type": "check"
			}
		},
		{
			"field": "K_B_00",
			"caption": "00",
			"size": "28px",
			"resizable": true,
			"editable": {
				"type": "text"
			}
		},
		{
			"field": "K_B_02",
			"caption": "02",
			"size": "28px",
			"resizable": true,
			"editable": {
				"type": "text"
			}
		},
		{
			"field": "K_B_10",
			"caption": "10",
			"size": "28px",
			"resizable": true,
			"editable": {
				"type": "text"
			}
		},
		{
			"field": "K_B_12",
			"caption": "12",
			"size": "45px",
			"resizable": true,
			"editable": {
				"type": "text"
			}
		},
		{
			"field": "K_A_0",
			"caption": "0",
			"size": "20px",
			"resizable": true,
			"editable": {
				"type": "text"
			}
		},
		{
			"field": "K_A_1",
			"caption": "1",
			"size": "20px",
			"resizable": true,
			"editable": {
				"type": "text"
			}
		}
	],
	"groups": [
		{
			"caption": "",
			"columns": [],
			"span": 1,
			"master": true,
			"hideable": false,
			"checked": false
		},
		{
			"caption": "K<sub>B</sub>(A,B)",
			"columns": [
				"K_B_00",
				"K_B_02",
				"K_B_10",
				"K_B_12"
			],
			"hideable": true,
			"checked": false,
			"span": 4,
			"text": "K<sub>B</sub>(A,B)",
			"icon": "w2ui-icon-cross"
		},
		{
			"caption": "K<sub>A</sub>(B)",
			"columns": [
				"K_A_0",
				"K_A_1"
			],
			"hideable": true,
			"checked": false,
			"span": 2,
			"text": "K<sub>A</sub>(B)",
			"icon": "w2ui-icon-cross"
		}
	],
	"configured": true,
	"name": "grid"
}